{
  "count": 116,
  "start": null,
  "limit": 1,
  "changesets": [
    {
      "node": "5bf6aff99e83",
      "files": [
        {
          "type": "modified",
          "file": "robots.txt"
        }
      ],
      "raw_author": "Dmitry Galinsky <dima.exe@gmail.com>",
      "utctimestamp": "2014-10-22 20:40:03+00:00",
      "author": "dmexe",
      "timestamp": "2014-10-22 22:40:03",
      "raw_node": "5bf6aff99e8350c493ecce2016c50d977de88d6f",
      "parents": [
        "b14806535f5e"
      ],
      "branch": "test",
      "message": "test\n",
      "revision": null,
      "size": -1
    }
  ]
}
